robot_doc_only/__init__.py
robot_doc_only/testdoc.py
robot_doc_only/testdoc_322.py
robot_doc_only/testdoc_400.py
robot_doc_only/version.py
robotframework_doc_only-0.1.2.dist-info/licenses/LICENSE
robotframework_doc_only-0.1.2.dist-info/METADATA
robotframework_doc_only-0.1.2.dist-info/WHEEL
robotframework_doc_only-0.1.2.dist-info/entry_points.txt
robotframework_doc_only-0.1.2.dist-info/top_level.txt
robotframework_doc_only-0.1.2.dist-info/zip-safe
robotframework_doc_only-0.1.2.dist-info/RECORD
