Metadata-Version: 2.4
Name: robotframework-doc-only
Version: 0.1.2
Summary: Create test documentation without technical details
Home-page: https://github.com/bli74/robotframework-doc-only/
Author: Bert Lindemann
Author-email: Bert Lindemann <bert.lindemann@gmail.com>
Maintainer: Bert Lindemann
Maintainer-email: Bert Lindemann <bert.lindemann@gmail.com>
License: Apache License 2.0
Project-URL: Homepage, https://github.com/bli74/robotframework-doc-only/
Project-URL: Repository, https://github.com/bli74/robotframework-doc-only/
Keywords: robotframework
Classifier: Development Status :: 5 - Production/Stable
Classifier: License :: OSI Approved :: Apache Software License
Classifier: Operating System :: OS Independent
Classifier: Framework :: Robot Framework
Classifier: Programming Language :: Python :: 3
Classifier: Topic :: Software Development :: Testing
Classifier: Topic :: Software Development :: Quality Assurance
Classifier: Intended Audience :: Developers
Requires-Python: >=3.6
License-File: LICENSE
Requires-Dist: robotframework>=3.2.2
Requires-Dist: packaging>=20.0
Dynamic: author
Dynamic: home-page
Dynamic: license-file
Dynamic: maintainer
Dynamic: requires-python
